odut/__init__.py
odut/cli.py
odut/utils.py
odut-1.6.0.dist-info/AUTHORS.rst
odut-1.6.0.dist-info/METADATA
odut-1.6.0.dist-info/WHEEL
odut-1.6.0.dist-info/entry_points.txt
odut-1.6.0.dist-info/top_level.txt
odut-1.6.0.dist-info/RECORD
