Metadata-Version: 2.1
Name: odut
Version: 1.6.0
Summary: Odoo utility functions with command line interfaces.
Home-page: https://github.com/minglyu/odut
Author: ming_lyu
Author-email: minglyupolimi@gmail.com
License: UNKNOWN
Keywords: odut
Platform: UNKNOWN
Classifier: Development Status :: 2 - Pre-Alpha
Classifier: Intended Audience :: Developers
Classifier: Natural Language :: English
Classifier: Programming Language :: Python :: 2
Classifier: Programming Language :: Python :: 2.7
Classifier: Programming Language :: Python :: 3
Classifier: Programming Language :: Python :: 3.4
Classifier: Programming Language :: Python :: 3.5
Classifier: Programming Language :: Python :: 3.6
Classifier: Programming Language :: Python :: 3.7
Requires-Dist: Click (>=6.0)
